AUTHORS
CHANGES
LICENSE
MANIFEST.in
README.rst
hamlish_jinja.py
setup.py
Hamlish_Jinja.egg-info/PKG-INFO
Hamlish_Jinja.egg-info/SOURCES.txt
Hamlish_Jinja.egg-info/dependency_links.txt
Hamlish_Jinja.egg-info/not-zip-safe
Hamlish_Jinja.egg-info/requires.txt
Hamlish_Jinja.egg-info/top_level.txt
tests/alltests.py
tests/test_compact_output.py
tests/test_debug_output.py
tests/test_div_shortcut.py
tests/test_haml_tags.py
tests/test_html_tags.py
tests/test_jinja_tags.py
tests/test_syntax.py
tests/testing_base.py