Metadata-Version: 1.1
Name: Hamlish-Jinja
Version: 0.3.2
Summary: Haml-ish syntax for jinja2 templates
Home-page: http://github.com/Pitmairen/hamlish-jinja
Author: Per Myren
Author-email: progrper@gmail.com
License: UNKNOWN
Keywords: jinja2 templates haml
Platform: any
Classifier: Development Status :: 4 - Beta
Classifier: Environment :: Web Environment
Classifier: Intended Audience :: Developers
Classifier: License :: OSI Approved :: BSD License
Classifier: Operating System :: OS Independent
Classifier: Programming Language :: Python
Classifier: Programming Language :: Python :: 3.3
Classifier: Topic :: Internet :: WWW/HTTP :: Dynamic Content
Classifier: Topic :: Software Development :: Libraries :: Python Modules
Classifier: Topic :: Text Processing :: Markup :: HTML
